sentileye/__init__.py
sentileye/booster.py
sentileye/emoticon.py
sentileye/emotion_new.csv
sentileye/neg.txt
sentileye/neg1.txt
sentileye/polarity.py
sentileye/sentileye_list.csv
sentileye/slang.csv
Leye-0.0.1.dist-info/LICENSE.txt
Leye-0.0.1.dist-info/METADATA
Leye-0.0.1.dist-info/WHEEL
Leye-0.0.1.dist-info/top_level.txt
Leye-0.0.1.dist-info/RECORD
